snaketest/__init__.py
snaketest-0.0.4.dist-info/LICENSE
snaketest-0.0.4.dist-info/METADATA
snaketest-0.0.4.dist-info/WHEEL
snaketest-0.0.4.dist-info/top_level.txt
snaketest-0.0.4.dist-info/RECORD
