Metadata-Version: 2.1
Name: snaketest
Version: 0.0.4
Summary: A small package to help test and prototype snakemake rules
Home-page: https://github.com/aLahat/snaketest
Author: Albert
License: MIT License
Classifier: Development Status :: 1 - Planning
Classifier: Intended Audience :: Science/Research
Classifier: License :: OSI Approved :: BSD License
Classifier: Operating System :: POSIX :: Linux
Classifier: Programming Language :: Python :: 3.5
License-File: LICENSE
